mwings/__init__.py
mwings/common.py
mwings/parsers/__init__.py
mwings/parsers/act.py
mwings/parsers/app_aria.py
mwings/parsers/app_cue.py
mwings/parsers/app_cue_pal_event.py
mwings/parsers/app_io.py
mwings/parsers/app_pal_amb.py
mwings/parsers/app_pal_mot.py
mwings/parsers/app_pal_openclose.py
mwings/parsers/app_twelite.py
mwings/parsers/app_uart_ascii.py
mwings/parsers/app_uart_ascii_extended.py
mwings/py.typed
mwings/serializers/__init__.py
mwings/serializers/app_io.py
mwings/serializers/app_pal_notice.py
mwings/serializers/app_pal_notice_detailed.py
mwings/serializers/app_pal_notice_event.py
mwings/serializers/app_twelite.py
mwings/serializers/app_uart_ascii.py
mwings/utils.py
mwings-1.0.18.dist-info/LICENSE
mwings-1.0.18.dist-info/METADATA
mwings-1.0.18.dist-info/WHEEL
mwings-1.0.18.dist-info/RECORD
